p2plantaccess/__init__.py
p2plantaccess/ipc.py
p2plantaccess/p2plantaccess.py
p2plantaccess/simulatedADCs.py
p2plantaccess-1.0.4.dist-info/METADATA
p2plantaccess-1.0.4.dist-info/WHEEL
p2plantaccess-1.0.4.dist-info/licenses/LICENSE
p2plantaccess-1.0.4.dist-info/RECORD
