Metadata-Version: 2.4
Name: p2plantaccess
Version: 1.0.4
Summary: Access to process variable of a P2Plant
Project-URL: Homepage, https://github.com/ASukhanov/p2plantaccess
Project-URL: Bug Tracker, https://github.com/ASukhanov/p2plantaccess/issues
Author-email: Andrei Sukhanov <cyxandr@gmail.com>
License-File: LICENSE
Classifier: License :: OSI Approved :: MIT License
Classifier: Operating System :: OS Independent
Classifier: Programming Language :: Python :: 3
Requires-Python: >=3.7
Requires-Dist: cbor2
